os_vm_expire/__init__.py
os_vm_expire/context.py
os_vm_expire/i18n.py
os_vm_expire/version.py
os_vm_expire/api/__init__.py
os_vm_expire/api/app.py
os_vm_expire/api/app.wsgi
os_vm_expire/api/hooks.py
os_vm_expire/api/controllers/__init__.py
os_vm_expire/api/controllers/versions.py
os_vm_expire/api/controllers/vmexclude.py
os_vm_expire/api/controllers/vmexpire.py
os_vm_expire/api/middleware/__init__.py
os_vm_expire/api/middleware/context.py
os_vm_expire/cmd/__init__.py
os_vm_expire/cmd/cleaner.py
os_vm_expire/cmd/db_manage.py
os_vm_expire/cmd/expire_manage.py
os_vm_expire/cmd/worker.py
os_vm_expire/common/__init__.py
os_vm_expire/common/config.py
os_vm_expire/common/hrefs.py
os_vm_expire/common/utils.py
os_vm_expire/common/policies/__init__.py
os_vm_expire/common/policies/acls.py
os_vm_expire/common/policies/base.py
os_vm_expire/model/__init__.py
os_vm_expire/model/clean.py
os_vm_expire/model/models.py
os_vm_expire/model/repositories.py
os_vm_expire/model/migration/__init__.py
os_vm_expire/model/migration/alembic.ini
os_vm_expire/model/migration/commands.py
os_vm_expire/model/migration/alembic_migrations/__init__.py
os_vm_expire/model/migration/alembic_migrations/env.py
os_vm_expire/model/migration/alembic_migrations/script.py.mako
os_vm_expire/model/migration/alembic_migrations/vmexpire_init_ops.py
os_vm_expire/model/migration/alembic_migrations/versions/3cf9516e9a67_create_exclude_table.py
os_vm_expire/model/migration/alembic_migrations/versions/initial.py
os_vm_expire/queue/__init__.py
os_vm_expire/queue/server.py
os_vm_expire/tests/__init__.py
os_vm_expire/tests/base.py
os_vm_expire/tests/database_utils.py
os_vm_expire/tests/test_os_vm_expire.py
os_vm_expire/tests/utils.py
os_vm_expire/tests/api/__init__.py
os_vm_expire/tests/api/test_resources_policy.py
os_vm_expire/tests/api/cmd/__init__.py
os_vm_expire/tests/api/cmd/test_cleaner.py
os_vm_expire/tests/api/cmd/test_worker.py
os_vm_expire/tests/api/controllers/__init__.py
os_vm_expire-0.9.12.dist-info/AUTHORS
os_vm_expire-0.9.12.dist-info/LICENSE
os_vm_expire-0.9.12.dist-info/METADATA
os_vm_expire-0.9.12.dist-info/WHEEL
os_vm_expire-0.9.12.dist-info/entry_points.txt
os_vm_expire-0.9.12.dist-info/pbr.json
os_vm_expire-0.9.12.dist-info/top_level.txt
os_vm_expire-0.9.12.dist-info/RECORD
