Metadata-Version: 2.1
Name: os-vm-expire
Version: 0.9.12
Summary: Manage VM expiration and deletion
Home-page: https://github.com/genouest/os-vm-expire
Author: Olivier Sallou
Author-email: olivier.sallou@irisa.fr
License: UNKNOWN
Platform: UNKNOWN
Classifier: Environment :: OpenStack
Classifier: Intended Audience :: Information Technology
Classifier: Intended Audience :: System Administrators
Classifier: License :: OSI Approved :: Apache Software License
Classifier: Operating System :: POSIX :: Linux
Classifier: Programming Language :: Python
Classifier: Programming Language :: Python :: 2
Classifier: Programming Language :: Python :: 2.7
Classifier: Programming Language :: Python :: 3
Classifier: Programming Language :: Python :: 3.3
Classifier: Programming Language :: Python :: 3.4
Requires-Dist: pbr
Requires-Dist: Paste (>=2.0.2)
Requires-Dist: PasteDeploy (>=1.5.0)
Requires-Dist: oslo.config (>=4.6.0)
Requires-Dist: oslo.context (>=2.19.2)
Requires-Dist: oslo.db (>=4.27.0)
Requires-Dist: oslo.policy
Requires-Dist: oslo.messaging
Requires-Dist: oslo.log
Requires-Dist: oslo.utils (>=3.31.0)
Requires-Dist: oslo.middleware (>=3.31.0)
Requires-Dist: oslo.i18n
Requires-Dist: oslo.service
Requires-Dist: WebOb
Requires-Dist: keystonemiddleware
Requires-Dist: pecan (!=1.0.2,!=1.0.3,!=1.0.4,!=1.2,>=1.0.0)
Requires-Dist: six (>=1.9.0)
Requires-Dist: SQLAlchemy (!=1.1.5,!=1.1.6,!=1.1.7,!=1.1.8,>=1.0.10)
Requires-Dist: alembic (>=0.8.10)
Requires-Dist: prettytable
